digitalkin_proto/__init__.py
digitalkin_proto/py.typed
digitalkin_proto/buf/__init__.py
digitalkin_proto/buf/validate/__init__.py
digitalkin_proto/buf/validate/expression_pb2.py
digitalkin_proto/buf/validate/expression_pb2.pyi
digitalkin_proto/buf/validate/expression_pb2_grpc.py
digitalkin_proto/buf/validate/validate_pb2.py
digitalkin_proto/buf/validate/validate_pb2.pyi
digitalkin_proto/buf/validate/validate_pb2_grpc.py
digitalkin_proto/buf/validate/priv/__init__.py
digitalkin_proto/buf/validate/priv/private_pb2.py
digitalkin_proto/buf/validate/priv/private_pb2.pyi
digitalkin_proto/buf/validate/priv/private_pb2_grpc.py
digitalkin_proto/digitalkin/__init__.py
digitalkin_proto/digitalkin/cost/__init__.py
digitalkin_proto/digitalkin/cost/v1/__init__.py
digitalkin_proto/digitalkin/cost/v1/cost_pb2.py
digitalkin_proto/digitalkin/cost/v1/cost_pb2.pyi
digitalkin_proto/digitalkin/cost/v1/cost_pb2_grpc.py
digitalkin_proto/digitalkin/cost/v1/cost_service_pb2.py
digitalkin_proto/digitalkin/cost/v1/cost_service_pb2.pyi
digitalkin_proto/digitalkin/cost/v1/cost_service_pb2_grpc.py
digitalkin_proto/digitalkin/filesystem/__init__.py
digitalkin_proto/digitalkin/filesystem/v1/__init__.py
digitalkin_proto/digitalkin/filesystem/v1/filesystem_pb2.py
digitalkin_proto/digitalkin/filesystem/v1/filesystem_pb2.pyi
digitalkin_proto/digitalkin/filesystem/v1/filesystem_pb2_grpc.py
digitalkin_proto/digitalkin/filesystem/v1/filesystem_service_pb2.py
digitalkin_proto/digitalkin/filesystem/v1/filesystem_service_pb2.pyi
digitalkin_proto/digitalkin/filesystem/v1/filesystem_service_pb2_grpc.py
digitalkin_proto/digitalkin/filesystem/v2/__init__.py
digitalkin_proto/digitalkin/filesystem/v2/filesystem_pb2.py
digitalkin_proto/digitalkin/filesystem/v2/filesystem_pb2.pyi
digitalkin_proto/digitalkin/filesystem/v2/filesystem_pb2_grpc.py
digitalkin_proto/digitalkin/filesystem/v2/filesystem_service_pb2.py
digitalkin_proto/digitalkin/filesystem/v2/filesystem_service_pb2.pyi
digitalkin_proto-0.1.16.dist-info/licenses/LICENSE
digitalkin_proto-0.1.16.dist-info/METADATA
digitalkin_proto-0.1.16.dist-info/WHEEL
digitalkin_proto-0.1.16.dist-info/top_level.txt
digitalkin_proto-0.1.16.dist-info/RECORD
