Metadata-Version: 2.4
Name: digitalkin_proto
Version: 0.1.16
Summary: Python Generated gRPC client and server interfaces from Digitalkin's service apis
Author-email: "DigitalKin.ai" <contact@digitalkin.ai>
Project-URL: Homepage, https://github.com/DigitalKin-ai/service-apis-py
Project-URL: Bug Tracker, https://github.com/DigitalKin-ai/service-apis-py/issues
Project-URL: Documentation, https://github.com/DigitalKin-ai/service-apis-py/blob/main/README.md
Keywords: digitalkin,kin,agent,gprc,sdk
Classifier: Development Status :: 3 - Alpha
Classifier: Intended Audience :: Developers
Classifier: Operating System :: OS Independent
Classifier: Topic :: Software Development :: Libraries
Classifier: Programming Language :: Python
Classifier: Programming Language :: Python :: 3.10
Classifier: Programming Language :: Python :: 3.11
Classifier: Programming Language :: Python :: 3.12
Classifier: Programming Language :: Python :: 3.13
Classifier: Programming Language :: Python :: 3 :: Only
Classifier: Typing :: Typed
Classifier: License :: Other/Proprietary License
Requires-Python: >=3.10
License-File: LICENSE
Requires-Dist: googleapis-common-protos>=1.70.0
Requires-Dist: protovalidate>=0.9.0
Requires-Dist: grpcio>=1.71.0
Requires-Dist: grpcio-tools>=1.71.0
Requires-Dist: protobuf<6.0.0,>=5.29.5
Provides-Extra: dev
Requires-Dist: pytest>=8.3.4; extra == "dev"
Requires-Dist: ruff>=0.11.11; extra == "dev"
Requires-Dist: mypy>=1.15.0; extra == "dev"
Requires-Dist: pre-commit>=4.2.0; extra == "dev"
Requires-Dist: bump2version>=1.0.1; extra == "dev"
Requires-Dist: build>=1.2.2; extra == "dev"
Requires-Dist: twine>=6.1.0; extra == "dev"
Dynamic: license-file
